isprime/__init__.py
isprime/core.py
isprime_kaatre-0.1.0.dist-info/licenses/LICENSE
isprime_kaatre-0.1.0.dist-info/METADATA
isprime_kaatre-0.1.0.dist-info/WHEEL
isprime_kaatre-0.1.0.dist-info/top_level.txt
isprime_kaatre-0.1.0.dist-info/RECORD
