Metadata-Version: 2.4
Name: isprime-kaatre
Version: 0.1.0
Summary: A simple package to check for prime numbers
Author-email: Manish Rakaskoti <newfeed4554@gmail.com>
License: MIT
Project-URL: Homepage, https://github.com/kaatreHx/isprime
Requires-Python: >=3.7
License-File: LICENSE
Dynamic: license-file
